[{
  "_id": {
    "$oid": "5fe64f9a74c4ad0d1c7f59a0"
  },
  "screen_name": "Premium",
  "rows": "2",
  "cols": "20",
  "user_id": {
    "$oid": "5fe49ff83daf9a35185ba919"
  },
  "__v": 0
},{
  "_id": {
    "$oid": "5fe8f0026affc50adca0cf88"
  },
  "screen_name": "Gold",
  "rows": "5",
  "cols": "10",
  "user_id": {
    "$oid": "5fe49ff83daf9a35185ba919"
  },
  "__v": 0
},{
  "_id": {
    "$oid": "5fef4c1d745de52f803cea6f"
  },
  "screen_name": "hellog",
  "rows": "4",
  "cols": "5",
  "user_id": {
    "$oid": "5fef47b012e94126845d081a"
  },
  "__v": 0
},{
  "_id": {
    "$oid": "5ff9ae1964bece2c3c67df5b"
  },
  "screen_name": "Premium",
  "rows": "5",
  "cols": "15",
  "user_id": {
    "$oid": "5ff1ed296482690cc073d10f"
  },
  "__v": 0
},{
  "_id": {
    "$oid": "5ffbf2878a201a43340835f0"
  },
  "screen_name": "Master ",
  "rows": "2",
  "cols": "8",
  "user_id": {
    "$oid": "5ffbf2538a201a43340835ef"
  },
  "__v": 0
}]